LICENSE
README.md
aliyunpan.py
requirements.txt
setup.py
aliyunpan/__init__.py
aliyunpan/about.py
aliyunpan/common.py
aliyunpan/exceptions.py
aliyunpan/main.py
aliyunpan.egg-info/PKG-INFO
aliyunpan.egg-info/SOURCES.txt
aliyunpan.egg-info/dependency_links.txt
aliyunpan.egg-info/entry_points.txt
aliyunpan.egg-info/not-zip-safe
aliyunpan.egg-info/requires.txt
aliyunpan.egg-info/top_level.txt
aliyunpan/api/__init__.py
aliyunpan/api/core.py
aliyunpan/api/models.py
aliyunpan/api/req.py
aliyunpan/api/type.py
aliyunpan/api/ua.py
aliyunpan/api/utils.py
aliyunpan/cli/__init__.py
aliyunpan/cli/cli.py
aliyunpan/cli/config.py
aliyunpan/cli/tui.py
dlnap/dlnap/dlnap.py