Metadata-Version: 2.1
Name: aliyunpan
Version: 3.0.8
Summary: aliyunpan cli
Home-page: https://github.com/wxy1343/aliyunpan
Author: wxy1343
Author-email: 1343890272@qq.com
License: UNKNOWN
Project-URL: Bug Reports, https://github.com/wxy1343/aliyunpan/issues
Project-URL: Funding, https://donate.pypi.org
Project-URL: Say Thanks!, https://saythanks.io/to/1343890272@qq.com
Project-URL: Source, https://github.com/wxy1343/aliyunpan
Keywords: aliyunpan,aliyundrive,cli,tui
Platform: UNKNOWN
Classifier: Development Status :: 4 - Beta
Classifier: Intended Audience :: Developers
Classifier: Intended Audience :: End Users/Desktop
Classifier: Environment :: Console
Classifier: Environment :: Console :: Curses
Classifier: Framework :: Flask
Classifier: Topic :: Internet
Classifier: Topic :: Internet :: WWW/HTTP
Classifier: Topic :: Multimedia
Classifier: Topic :: Multimedia :: Graphics
Classifier: Topic :: Multimedia :: Sound/Audio
Classifier: Topic :: Multimedia :: Video
Classifier: Topic :: Communications :: File Sharing
Classifier: Topic :: Utilities
Classifier: License :: OSI Approved :: GNU General Public License v3 (GPLv3)
Classifier: Programming Language :: Python :: 3
Classifier: Programming Language :: Python :: 3.6
Classifier: Programming Language :: Python :: 3.7
Classifier: Programming Language :: Python :: 3.8
Classifier: Programming Language :: Python :: 3.9
Classifier: Programming Language :: Python :: 3.10
Classifier: Programming Language :: Python :: 3 :: Only
Requires-Python: >=3.6, <4
License-File: LICENSE
